LICENSE
MANIFEST.in
README.md
pyproject.toml
setup.py
src/bitermplus/__init__.py
src/bitermplus/_api.py
src/bitermplus/_btm.c
src/bitermplus/_btm.pyx
src/bitermplus/_metrics.c
src/bitermplus/_metrics.pyx
src/bitermplus/_util.py
src/bitermplus.egg-info/PKG-INFO
src/bitermplus.egg-info/SOURCES.txt
src/bitermplus.egg-info/dependency_links.txt
src/bitermplus.egg-info/not-zip-safe
src/bitermplus.egg-info/requires.txt
src/bitermplus.egg-info/top_level.txt
tests/test_btm.py
tests/test_btm_classifier.py
tests/test_sklearn_api.py