Metadata-Version: 2.4
Name: bitermplus
Version: 0.9.1
Summary: Biterm Topic Model with sklearn-compatible API
Author-email: Maksim Terpilovskii <maximtrp@gmail.com>
Maintainer-email: Maksim Terpilovskii <maximtrp@gmail.com>
Project-URL: Homepage, https://github.com/maximtrp/bitermplus
Project-URL: Documentation, https://bitermplus.readthedocs.io/
Project-URL: Repository, https://github.com/maximtrp/bitermplus.git
Project-URL: Bug Tracker, https://github.com/maximtrp/bitermplus/issues
Keywords: topic-modeling,machine-learning,nlp,biterm,sklearn,text-mining,unsupervised-learning
Classifier: Development Status :: 4 - Beta
Classifier: Intended Audience :: Developers
Classifier: Intended Audience :: Science/Research
Classifier: Operating System :: OS Independent
Classifier: Programming Language :: Python :: 3
Classifier: Programming Language :: Python :: 3.9
Classifier: Programming Language :: Python :: 3.10
Classifier: Programming Language :: Python :: 3.11
Classifier: Programming Language :: Python :: 3.12
Classifier: Programming Language :: Python :: 3.13
Classifier: Programming Language :: Cython
Classifier: Topic :: Scientific/Engineering :: Artificial Intelligence
Classifier: Topic :: Scientific/Engineering :: Information Analysis
Classifier: Topic :: Text Processing :: Linguistic
Classifier: Topic :: Software Development :: Libraries :: Python Modules
Classifier: Typing :: Typed
Requires-Python: >=3.9
License-File: LICENSE
Requires-Dist: numpy>=1.19.0
Requires-Dist: pandas>=1.2.0
Requires-Dist: scipy>=1.6.0
Requires-Dist: scikit-learn>=1.0.0
Requires-Dist: tqdm>=4.50.0
Provides-Extra: dev
Requires-Dist: pytest>=6.0; extra == "dev"
Requires-Dist: pytest-cov>=2.10; extra == "dev"
Requires-Dist: black>=22.0; extra == "dev"
Requires-Dist: isort>=5.10; extra == "dev"
Requires-Dist: flake8>=4.0; extra == "dev"
Requires-Dist: mypy>=0.950; extra == "dev"
Requires-Dist: pre-commit>=2.15; extra == "dev"
Requires-Dist: cython>=3.0.0; extra == "dev"
Provides-Extra: docs
Requires-Dist: sphinx>=4.0; extra == "docs"
Requires-Dist: sphinx-rtd-theme>=1.0; extra == "docs"
Requires-Dist: nbsphinx>=0.8; extra == "docs"
Requires-Dist: jupyter>=1.0; extra == "docs"
Provides-Extra: test
Requires-Dist: pytest>=6.0; extra == "test"
Requires-Dist: pytest-cov>=2.10; extra == "test"
Requires-Dist: cython>=3.0.0; extra == "test"
Provides-Extra: benchmark
Requires-Dist: matplotlib>=3.3; extra == "benchmark"
Requires-Dist: seaborn>=0.11; extra == "benchmark"
Requires-Dist: gensim>=4.0; extra == "benchmark"
Dynamic: license-file
